meroua/__init__.py
meroua/mymod.py
meroua-1.2.dist-info/LICENCE.TXT
meroua-1.2.dist-info/METADATA
meroua-1.2.dist-info/WHEEL
meroua-1.2.dist-info/top_level.txt
meroua-1.2.dist-info/RECORD
